{
    "design__instance__count": 5748,
    "design__instance__area": 24274.5,
    "design__instance_unmapped__count": 0,
    "synthesis__check_error__count": 0,
    "design__max_slew_violation__count__corner:nom_tt_025C_1v80": 0,
    "design__max_fanout_violation__count__corner:nom_tt_025C_1v80": 0,
    "design__max_cap_violation__count__corner:nom_tt_025C_1v80": 0,
    "power__internal__total": 0.023867780342698097,
    "power__switching__total": 0.03149837628006935,
    "power__leakage__total": 3.0825624719454936e-08,
    "power__total": 0.055366188287734985,
    "clock__skew__worst_hold__corner:nom_tt_025C_1v80": -0.1405339079329767,
    "clock__skew__worst_setup__corner:nom_tt_025C_1v80": 0.15054889705445612,
    "timing__hold__ws__corner:nom_tt_025C_1v80": 0.3385397058508422,
    "timing__setup__ws__corner:nom_tt_025C_1v80": 12.0291762178231,
    "timing__hold__tns__corner:nom_tt_025C_1v80": 0,
    "timing__setup__tns__corner:nom_tt_025C_1v80": 0,
    "timing__hold__wns__corner:nom_tt_025C_1v80": 0,
    "timing__setup__wns__corner:nom_tt_025C_1v80": 0,
    "timing__hold_vio__count__corner:nom_tt_025C_1v80": 0,
    "timing__hold_r2r__ws__corner:nom_tt_025C_1v80": 0.33854,
    "timing__hold_r2r_vio__count__corner:nom_tt_025C_1v80": 0,
    "timing__setup_vio__count__corner:nom_tt_025C_1v80": 0,
    "timing__setup_r2r__ws__corner:nom_tt_025C_1v80": 12.029176,
    "timing__setup_r2r_vio__count__corner:nom_tt_025C_1v80": 0,
    "design__max_slew_violation__count__corner:nom_ss_100C_1v60": 0,
    "design__max_fanout_violation__count__corner:nom_ss_100C_1v60": 0,
    "design__max_cap_violation__count__corner:nom_ss_100C_1v60": 0,
    "clock__skew__worst_hold__corner:nom_ss_100C_1v60": -0.15747935345938288,
    "clock__skew__worst_setup__corner:nom_ss_100C_1v60": 0.17571415653190298,
    "timing__hold__ws__corner:nom_ss_100C_1v60": 0.8157587058973605,
    "timing__setup__ws__corner:nom_ss_100C_1v60": -0.5999094724120118,
    "timing__hold__tns__corner:nom_ss_100C_1v60": 0,
    "timing__setup__tns__corner:nom_ss_100C_1v60": -2.9211016654567086,
    "timing__hold__wns__corner:nom_ss_100C_1v60": 0,
    "timing__setup__wns__corner:nom_ss_100C_1v60": -0.5999094724120118,
    "timing__hold_vio__count__corner:nom_ss_100C_1v60": 0,
    "timing__hold_r2r__ws__corner:nom_ss_100C_1v60": 0.815759,
    "timing__hold_r2r_vio__count__corner:nom_ss_100C_1v60": 0,
    "timing__setup_vio__count__corner:nom_ss_100C_1v60": 8,
    "timing__setup_r2r__ws__corner:nom_ss_100C_1v60": -0.599909,
    "timing__setup_r2r_vio__count__corner:nom_ss_100C_1v60": 8,
    "design__max_slew_violation__count__corner:nom_ff_n40C_1v95": 0,
    "design__max_fanout_violation__count__corner:nom_ff_n40C_1v95": 0,
    "design__max_cap_violation__count__corner:nom_ff_n40C_1v95": 0,
    "clock__skew__worst_hold__corner:nom_ff_n40C_1v95": -0.1320632945935801,
    "clock__skew__worst_setup__corner:nom_ff_n40C_1v95": 0.1379993242072258,
    "timing__hold__ws__corner:nom_ff_n40C_1v95": 0.17584995068944298,
    "timing__setup__ws__corner:nom_ff_n40C_1v95": 16.99170985341836,
    "timing__hold__tns__corner:nom_ff_n40C_1v95": 0,
    "timing__setup__tns__corner:nom_ff_n40C_1v95": 0,
    "timing__hold__wns__corner:nom_ff_n40C_1v95": 0,
    "timing__setup__wns__corner:nom_ff_n40C_1v95": 0,
    "timing__hold_vio__count__corner:nom_ff_n40C_1v95": 0,
    "timing__hold_r2r__ws__corner:nom_ff_n40C_1v95": 0.17585,
    "timing__hold_r2r_vio__count__corner:nom_ff_n40C_1v95": 0,
    "timing__setup_vio__count__corner:nom_ff_n40C_1v95": 0,
    "timing__setup_r2r__ws__corner:nom_ff_n40C_1v95": 16.991711,
    "timing__setup_r2r_vio__count__corner:nom_ff_n40C_1v95": 0,
    "design__max_slew_violation__count": 0,
    "design__max_fanout_violation__count": 0,
    "design__max_cap_violation__count": 0,
    "clock__skew__worst_hold": -0.1285063897222655,
    "clock__skew__worst_setup": 0.13441138860149532,
    "timing__hold__ws": 0.1745000582311993,
    "timing__setup__ws": -0.768057639228355,
    "timing__hold__tns": 0,
    "timing__setup__tns": -4.183325804170642,
    "timing__hold__wns": 0,
    "timing__setup__wns": -0.768057639228355,
    "timing__hold_vio__count": 0,
    "timing__hold_r2r__ws": 0.1745,
    "timing__hold_r2r_vio__count": 0,
    "timing__setup_vio__count": 23,
    "timing__setup_r2r__ws": -0.768058,
    "timing__setup_r2r_vio__count": 23,
    "design__die__bbox": "0.0 0.0 460.975 471.695",
    "design__core__bbox": "5.52 10.88 455.4 459.68",
    "design__io": 56,
    "design__die__area": 217440,
    "design__core__area": 201906,
    "design__instance__count__stdcell": 5748,
    "design__instance__area__stdcell": 24274.5,
    "design__instance__count__macros": 0,
    "design__instance__area__macros": 0,
    "design__instance__utilization": 0.120227,
    "design__instance__utilization__stdcell": 0.120227,
    "design__instance__count__class:buffer": 5,
    "design__instance__count__class:inverter": 65,
    "design__instance__count__class:sequential_cell": 169,
    "design__instance__count__class:multi_input_combinational_cell": 1685,
    "flow__warnings__count": 1,
    "flow__errors__count": 0,
    "design__instance__count__class:fill_cell": 16765,
    "design__instance__count__class:tap_cell": 2839,
    "design__power_grid_violation__count__net:VGND": 0,
    "design__power_grid_violation__count__net:VPWR": 0,
    "design__power_grid_violation__count": 0,
    "floorplan__design__io": 54,
    "design__io__hpwl": 5929205,
    "timing__drv__floating__nets": 0,
    "timing__drv__floating__pins": 0,
    "design__instance__displacement__total": 0,
    "design__instance__displacement__mean": 0,
    "design__instance__displacement__max": 0,
    "route__wirelength__estimated": 46566.6,
    "design__violations": 0,
    "design__instance__count__class:timing_repair_buffer": 58,
    "design__instance__count__class:clock_buffer": 19,
    "design__instance__count__class:clock_inverter": 13,
    "design__instance__count__setup_buffer": 5,
    "design__instance__count__hold_buffer": 0,
    "antenna__violating__nets": 0,
    "antenna__violating__pins": 0,
    "route__antenna_violation__count": 0,
    "design__instance__count__class:antenna_cell": 895,
    "antenna_diodes_count": 0,
    "route__net": 2036,
    "route__net__special": 2,
    "route__drc_errors__iter:1": 537,
    "route__wirelength__iter:1": 52830,
    "route__drc_errors__iter:2": 129,
    "route__wirelength__iter:2": 52465,
    "route__drc_errors__iter:3": 106,
    "route__wirelength__iter:3": 52439,
    "route__drc_errors__iter:4": 0,
    "route__wirelength__iter:4": 52452,
    "route__drc_errors": 0,
    "route__wirelength": 52452,
    "route__vias": 14814,
    "route__vias__singlecut": 14814,
    "route__vias__multicut": 0,
    "design__disconnected_pin__count": 0,
    "design__critical_disconnected_pin__count": 0,
    "route__wirelength__max": 948.92,
    "timing__unannotated_net__count__corner:nom_tt_025C_1v80": 15,
    "timing__unannotated_net_filtered__count__corner:nom_tt_025C_1v80": 0,
    "timing__unannotated_net__count__corner:nom_ss_100C_1v60": 15,
    "timing__unannotated_net_filtered__count__corner:nom_ss_100C_1v60": 0,
    "timing__unannotated_net__count__corner:nom_ff_n40C_1v95": 15,
    "timing__unannotated_net_filtered__count__corner:nom_ff_n40C_1v95": 0,
    "design__max_slew_violation__count__corner:min_tt_025C_1v80": 0,
    "design__max_fanout_violation__count__corner:min_tt_025C_1v80": 0,
    "design__max_cap_violation__count__corner:min_tt_025C_1v80": 0,
    "clock__skew__worst_hold__corner:min_tt_025C_1v80": -0.13651459515882797,
    "clock__skew__worst_setup__corner:min_tt_025C_1v80": 0.14641153981387556,
    "timing__hold__ws__corner:min_tt_025C_1v80": 0.3381933162573626,
    "timing__setup__ws__corner:min_tt_025C_1v80": 12.119398272426311,
    "timing__hold__tns__corner:min_tt_025C_1v80": 0,
    "timing__setup__tns__corner:min_tt_025C_1v80": 0,
    "timing__hold__wns__corner:min_tt_025C_1v80": 0,
    "timing__setup__wns__corner:min_tt_025C_1v80": 0,
    "timing__hold_vio__count__corner:min_tt_025C_1v80": 0,
    "timing__hold_r2r__ws__corner:min_tt_025C_1v80": 0.338193,
    "timing__hold_r2r_vio__count__corner:min_tt_025C_1v80": 0,
    "timing__setup_vio__count__corner:min_tt_025C_1v80": 0,
    "timing__setup_r2r__ws__corner:min_tt_025C_1v80": 12.119398,
    "timing__setup_r2r_vio__count__corner:min_tt_025C_1v80": 0,
    "timing__unannotated_net__count__corner:min_tt_025C_1v80": 15,
    "timing__unannotated_net_filtered__count__corner:min_tt_025C_1v80": 0,
    "design__max_slew_violation__count__corner:min_ss_100C_1v60": 0,
    "design__max_fanout_violation__count__corner:min_ss_100C_1v60": 0,
    "design__max_cap_violation__count__corner:min_ss_100C_1v60": 0,
    "clock__skew__worst_hold__corner:min_ss_100C_1v60": -0.15374206509704072,
    "clock__skew__worst_setup__corner:min_ss_100C_1v60": 0.16992695231891736,
    "timing__hold__ws__corner:min_ss_100C_1v60": 0.815972201791034,
    "timing__setup__ws__corner:min_ss_100C_1v60": -0.4629470271501718,
    "timing__hold__tns__corner:min_ss_100C_1v60": 0,
    "timing__setup__tns__corner:min_ss_100C_1v60": -1.830301295663613,
    "timing__hold__wns__corner:min_ss_100C_1v60": 0,
    "timing__setup__wns__corner:min_ss_100C_1v60": -0.4629470271501718,
    "timing__hold_vio__count__corner:min_ss_100C_1v60": 0,
    "timing__hold_r2r__ws__corner:min_ss_100C_1v60": 0.815972,
    "timing__hold_r2r_vio__count__corner:min_ss_100C_1v60": 0,
    "timing__setup_vio__count__corner:min_ss_100C_1v60": 7,
    "timing__setup_r2r__ws__corner:min_ss_100C_1v60": -0.462947,
    "timing__setup_r2r_vio__count__corner:min_ss_100C_1v60": 7,
    "timing__unannotated_net__count__corner:min_ss_100C_1v60": 15,
    "timing__unannotated_net_filtered__count__corner:min_ss_100C_1v60": 0,
    "design__max_slew_violation__count__corner:min_ff_n40C_1v95": 0,
    "design__max_fanout_violation__count__corner:min_ff_n40C_1v95": 0,
    "design__max_cap_violation__count__corner:min_ff_n40C_1v95": 0,
    "clock__skew__worst_hold__corner:min_ff_n40C_1v95": -0.1285063897222655,
    "clock__skew__worst_setup__corner:min_ff_n40C_1v95": 0.13441138860149532,
    "timing__hold__ws__corner:min_ff_n40C_1v95": 0.17566698592981014,
    "timing__setup__ws__corner:min_ff_n40C_1v95": 17.054173667085628,
    "timing__hold__tns__corner:min_ff_n40C_1v95": 0,
    "timing__setup__tns__corner:min_ff_n40C_1v95": 0,
    "timing__hold__wns__corner:min_ff_n40C_1v95": 0,
    "timing__setup__wns__corner:min_ff_n40C_1v95": 0,
    "timing__hold_vio__count__corner:min_ff_n40C_1v95": 0,
    "timing__hold_r2r__ws__corner:min_ff_n40C_1v95": 0.175667,
    "timing__hold_r2r_vio__count__corner:min_ff_n40C_1v95": 0,
    "timing__setup_vio__count__corner:min_ff_n40C_1v95": 0,
    "timing__setup_r2r__ws__corner:min_ff_n40C_1v95": 17.054174,
    "timing__setup_r2r_vio__count__corner:min_ff_n40C_1v95": 0,
    "timing__unannotated_net__count__corner:min_ff_n40C_1v95": 15,
    "timing__unannotated_net_filtered__count__corner:min_ff_n40C_1v95": 0,
    "design__max_slew_violation__count__corner:max_tt_025C_1v80": 0,
    "design__max_fanout_violation__count__corner:max_tt_025C_1v80": 0,
    "design__max_cap_violation__count__corner:max_tt_025C_1v80": 0,
    "clock__skew__worst_hold__corner:max_tt_025C_1v80": -0.1457944778393372,
    "clock__skew__worst_setup__corner:max_tt_025C_1v80": 0.15631206493827882,
    "timing__hold__ws__corner:max_tt_025C_1v80": 0.3371114594004196,
    "timing__setup__ws__corner:max_tt_025C_1v80": 11.941065363383222,
    "timing__hold__tns__corner:max_tt_025C_1v80": 0,
    "timing__setup__tns__corner:max_tt_025C_1v80": 0,
    "timing__hold__wns__corner:max_tt_025C_1v80": 0,
    "timing__setup__wns__corner:max_tt_025C_1v80": 0,
    "timing__hold_vio__count__corner:max_tt_025C_1v80": 0,
    "timing__hold_r2r__ws__corner:max_tt_025C_1v80": 0.337111,
    "timing__hold_r2r_vio__count__corner:max_tt_025C_1v80": 0,
    "timing__setup_vio__count__corner:max_tt_025C_1v80": 0,
    "timing__setup_r2r__ws__corner:max_tt_025C_1v80": 11.941066,
    "timing__setup_r2r_vio__count__corner:max_tt_025C_1v80": 0,
    "timing__unannotated_net__count__corner:max_tt_025C_1v80": 15,
    "timing__unannotated_net_filtered__count__corner:max_tt_025C_1v80": 0,
    "design__max_slew_violation__count__corner:max_ss_100C_1v60": 0,
    "design__max_fanout_violation__count__corner:max_ss_100C_1v60": 0,
    "design__max_cap_violation__count__corner:max_ss_100C_1v60": 0,
    "clock__skew__worst_hold__corner:max_ss_100C_1v60": -0.16371381103048796,
    "clock__skew__worst_setup__corner:max_ss_100C_1v60": 0.18266981500020152,
    "timing__hold__ws__corner:max_ss_100C_1v60": 0.8143433380343879,
    "timing__setup__ws__corner:max_ss_100C_1v60": -0.768057639228355,
    "timing__hold__tns__corner:max_ss_100C_1v60": 0,
    "timing__setup__tns__corner:max_ss_100C_1v60": -4.183325804170642,
    "timing__hold__wns__corner:max_ss_100C_1v60": 0,
    "timing__setup__wns__corner:max_ss_100C_1v60": -0.768057639228355,
    "timing__hold_vio__count__corner:max_ss_100C_1v60": 0,
    "timing__hold_r2r__ws__corner:max_ss_100C_1v60": 0.814343,
    "timing__hold_r2r_vio__count__corner:max_ss_100C_1v60": 0,
    "timing__setup_vio__count__corner:max_ss_100C_1v60": 8,
    "timing__setup_r2r__ws__corner:max_ss_100C_1v60": -0.768058,
    "timing__setup_r2r_vio__count__corner:max_ss_100C_1v60": 8,
    "timing__unannotated_net__count__corner:max_ss_100C_1v60": 15,
    "timing__unannotated_net_filtered__count__corner:max_ss_100C_1v60": 0,
    "design__max_slew_violation__count__corner:max_ff_n40C_1v95": 0,
    "design__max_fanout_violation__count__corner:max_ff_n40C_1v95": 0,
    "design__max_cap_violation__count__corner:max_ff_n40C_1v95": 0,
    "clock__skew__worst_hold__corner:max_ff_n40C_1v95": -0.13650529704073375,
    "clock__skew__worst_setup__corner:max_ff_n40C_1v95": 0.142903207201262,
    "timing__hold__ws__corner:max_ff_n40C_1v95": 0.1745000582311993,
    "timing__setup__ws__corner:max_ff_n40C_1v95": 16.92654952999262,
    "timing__hold__tns__corner:max_ff_n40C_1v95": 0,
    "timing__setup__tns__corner:max_ff_n40C_1v95": 0,
    "timing__hold__wns__corner:max_ff_n40C_1v95": 0,
    "timing__setup__wns__corner:max_ff_n40C_1v95": 0,
    "timing__hold_vio__count__corner:max_ff_n40C_1v95": 0,
    "timing__hold_r2r__ws__corner:max_ff_n40C_1v95": 0.1745,
    "timing__hold_r2r_vio__count__corner:max_ff_n40C_1v95": 0,
    "timing__setup_vio__count__corner:max_ff_n40C_1v95": 0,
    "timing__setup_r2r__ws__corner:max_ff_n40C_1v95": 16.92655,
    "timing__setup_r2r_vio__count__corner:max_ff_n40C_1v95": 0,
    "timing__unannotated_net__count__corner:max_ff_n40C_1v95": 15,
    "timing__unannotated_net_filtered__count__corner:max_ff_n40C_1v95": 0,
    "timing__unannotated_net__count": 15,
    "timing__unannotated_net_filtered__count": 0,
    "design_powergrid__voltage__worst__net:VPWR__corner:nom_tt_025C_1v80": 1.78987,
    "design_powergrid__drop__average__net:VPWR__corner:nom_tt_025C_1v80": 1.79948,
    "design_powergrid__drop__worst__net:VPWR__corner:nom_tt_025C_1v80": 0.010125,
    "design_powergrid__voltage__worst__net:VGND__corner:nom_tt_025C_1v80": 0.0107728,
    "design_powergrid__drop__average__net:VGND__corner:nom_tt_025C_1v80": 0.000526519,
    "design_powergrid__drop__worst__net:VGND__corner:nom_tt_025C_1v80": 0.0107728,
    "design_powergrid__voltage__worst": 0.0107728,
    "design_powergrid__voltage__worst__net:VPWR": 1.78987,
    "design_powergrid__drop__worst": 0.0107728,
    "design_powergrid__drop__worst__net:VPWR": 0.010125,
    "design_powergrid__voltage__worst__net:VGND": 0.0107728,
    "design_powergrid__drop__worst__net:VGND": 0.0107728,
    "ir__voltage__worst": 1.79,
    "ir__drop__avg": 0.000522,
    "ir__drop__worst": 0.0101,
    "design__xor_difference__count": 0,
    "magic__drc_error__count": 0,
    "klayout__drc_error__count": 0,
    "magic__illegal_overlap__count": 0,
    "design__lvs_device_difference__count": 0,
    "design__lvs_net_difference__count": 0,
    "design__lvs_property_fail__count": 0,
    "design__lvs_error__count": 0,
    "design__lvs_unmatched_device__count": 0,
    "design__lvs_unmatched_net__count": 0,
    "design__lvs_unmatched_pin__count": 0
}