{
    "design__instance__count": 5463,
    "design__instance__area": 21623.2,
    "design__instance_unmapped__count": 0,
    "synthesis__check_error__count": 0,
    "design__max_slew_violation__count__corner:nom_tt_025C_1v80": 0,
    "design__max_fanout_violation__count__corner:nom_tt_025C_1v80": 0,
    "design__max_cap_violation__count__corner:nom_tt_025C_1v80": 0,
    "power__internal__total": 0.013981081545352936,
    "power__switching__total": 0.0180838443338871,
    "power__leakage__total": 2.534728693603938e-08,
    "power__total": 0.032064951956272125,
    "clock__skew__worst_hold__corner:nom_tt_025C_1v80": -0.14189520793312105,
    "clock__skew__worst_setup__corner:nom_tt_025C_1v80": 0.13993349930427873,
    "timing__hold__ws__corner:nom_tt_025C_1v80": 0.3460580253639339,
    "timing__setup__ws__corner:nom_tt_025C_1v80": 14.410568257679218,
    "timing__hold__tns__corner:nom_tt_025C_1v80": 0,
    "timing__setup__tns__corner:nom_tt_025C_1v80": 0,
    "timing__hold__wns__corner:nom_tt_025C_1v80": 0,
    "timing__setup__wns__corner:nom_tt_025C_1v80": 0,
    "timing__hold_vio__count__corner:nom_tt_025C_1v80": 0,
    "timing__hold_r2r__ws__corner:nom_tt_025C_1v80": 0.346058,
    "timing__hold_r2r_vio__count__corner:nom_tt_025C_1v80": 0,
    "timing__setup_vio__count__corner:nom_tt_025C_1v80": 0,
    "timing__setup_r2r__ws__corner:nom_tt_025C_1v80": 14.410568,
    "timing__setup_r2r_vio__count__corner:nom_tt_025C_1v80": 0,
    "design__max_slew_violation__count__corner:nom_ss_100C_1v60": 0,
    "design__max_fanout_violation__count__corner:nom_ss_100C_1v60": 0,
    "design__max_cap_violation__count__corner:nom_ss_100C_1v60": 0,
    "clock__skew__worst_hold__corner:nom_ss_100C_1v60": -0.1620925523017755,
    "clock__skew__worst_setup__corner:nom_ss_100C_1v60": 0.160960013762325,
    "timing__hold__ws__corner:nom_ss_100C_1v60": 0.8048146266114471,
    "timing__setup__ws__corner:nom_ss_100C_1v60": 3.339915105683798,
    "timing__hold__tns__corner:nom_ss_100C_1v60": 0,
    "timing__setup__tns__corner:nom_ss_100C_1v60": 0,
    "timing__hold__wns__corner:nom_ss_100C_1v60": 0,
    "timing__setup__wns__corner:nom_ss_100C_1v60": 0,
    "timing__hold_vio__count__corner:nom_ss_100C_1v60": 0,
    "timing__hold_r2r__ws__corner:nom_ss_100C_1v60": 0.804815,
    "timing__hold_r2r_vio__count__corner:nom_ss_100C_1v60": 0,
    "timing__setup_vio__count__corner:nom_ss_100C_1v60": 0,
    "timing__setup_r2r__ws__corner:nom_ss_100C_1v60": 3.339915,
    "timing__setup_r2r_vio__count__corner:nom_ss_100C_1v60": 0,
    "design__max_slew_violation__count__corner:nom_ff_n40C_1v95": 0,
    "design__max_fanout_violation__count__corner:nom_ff_n40C_1v95": 0,
    "design__max_cap_violation__count__corner:nom_ff_n40C_1v95": 0,
    "clock__skew__worst_hold__corner:nom_ff_n40C_1v95": -0.13169286867093755,
    "clock__skew__worst_setup__corner:nom_ff_n40C_1v95": 0.12935723691682618,
    "timing__hold__ws__corner:nom_ff_n40C_1v95": 0.17831819858759643,
    "timing__setup__ws__corner:nom_ff_n40C_1v95": 18.59072237662341,
    "timing__hold__tns__corner:nom_ff_n40C_1v95": 0,
    "timing__setup__tns__corner:nom_ff_n40C_1v95": 0,
    "timing__hold__wns__corner:nom_ff_n40C_1v95": 0,
    "timing__setup__wns__corner:nom_ff_n40C_1v95": 0,
    "timing__hold_vio__count__corner:nom_ff_n40C_1v95": 0,
    "timing__hold_r2r__ws__corner:nom_ff_n40C_1v95": 0.178318,
    "timing__hold_r2r_vio__count__corner:nom_ff_n40C_1v95": 0,
    "timing__setup_vio__count__corner:nom_ff_n40C_1v95": 0,
    "timing__setup_r2r__ws__corner:nom_ff_n40C_1v95": 18.590723,
    "timing__setup_r2r_vio__count__corner:nom_ff_n40C_1v95": 0,
    "design__max_slew_violation__count": 0,
    "design__max_fanout_violation__count": 0,
    "design__max_cap_violation__count": 0,
    "clock__skew__worst_hold": -0.12827343716953518,
    "clock__skew__worst_setup": 0.1267288393428412,
    "timing__hold__ws": 0.17701399180810815,
    "timing__setup__ws": 3.212500578703768,
    "timing__hold__tns": 0,
    "timing__setup__tns": 0,
    "timing__hold__wns": 0,
    "timing__setup__wns": 0,
    "timing__hold_vio__count": 0,
    "timing__hold_r2r__ws": 0.177014,
    "timing__hold_r2r_vio__count": 0,
    "timing__setup_vio__count": 0,
    "timing__setup_r2r__ws": 3.212501,
    "timing__setup_r2r_vio__count": 0,
    "design__die__bbox": "0.0 0.0 443.985 454.705",
    "design__core__bbox": "5.52 10.88 438.38 443.36",
    "design__io": 56,
    "design__die__area": 201882,
    "design__core__area": 187203,
    "design__instance__count__stdcell": 5463,
    "design__instance__area__stdcell": 21623.2,
    "design__instance__count__macros": 0,
    "design__instance__area__macros": 0,
    "design__instance__utilization": 0.115507,
    "design__instance__utilization__stdcell": 0.115507,
    "design__instance__count__class:inverter": 65,
    "design__instance__count__class:sequential_cell": 165,
    "design__instance__count__class:multi_input_combinational_cell": 1595,
    "flow__warnings__count": 1,
    "flow__errors__count": 0,
    "design__instance__count__class:fill_cell": 15525,
    "design__instance__count__class:tap_cell": 2656,
    "design__power_grid_violation__count__net:VGND": 0,
    "design__power_grid_violation__count__net:VPWR": 0,
    "design__power_grid_violation__count": 0,
    "floorplan__design__io": 54,
    "design__io__hpwl": 5618066,
    "timing__drv__floating__nets": 0,
    "timing__drv__floating__pins": 0,
    "design__instance__displacement__total": 0,
    "design__instance__displacement__mean": 0,
    "design__instance__displacement__max": 0,
    "route__wirelength__estimated": 40589.7,
    "design__violations": 0,
    "design__instance__count__class:timing_repair_buffer": 48,
    "design__instance__count__class:clock_buffer": 18,
    "design__instance__count__class:clock_inverter": 14,
    "design__instance__count__setup_buffer": 0,
    "design__instance__count__hold_buffer": 0,
    "antenna__violating__nets": 0,
    "antenna__violating__pins": 0,
    "route__antenna_violation__count": 0,
    "design__instance__count__class:antenna_cell": 902,
    "antenna_diodes_count": 2,
    "route__net": 1927,
    "route__net__special": 2,
    "route__drc_errors__iter:1": 469,
    "route__wirelength__iter:1": 46303,
    "route__drc_errors__iter:2": 174,
    "route__wirelength__iter:2": 46063,
    "route__drc_errors__iter:3": 78,
    "route__wirelength__iter:3": 46051,
    "route__drc_errors__iter:4": 0,
    "route__wirelength__iter:4": 46036,
    "route__drc_errors": 0,
    "route__wirelength": 46036,
    "route__vias": 14465,
    "route__vias__singlecut": 14465,
    "route__vias__multicut": 0,
    "design__disconnected_pin__count": 0,
    "design__critical_disconnected_pin__count": 0,
    "route__wirelength__max": 994.405,
    "timing__unannotated_net__count__corner:nom_tt_025C_1v80": 20,
    "timing__unannotated_net_filtered__count__corner:nom_tt_025C_1v80": 0,
    "timing__unannotated_net__count__corner:nom_ss_100C_1v60": 20,
    "timing__unannotated_net_filtered__count__corner:nom_ss_100C_1v60": 0,
    "timing__unannotated_net__count__corner:nom_ff_n40C_1v95": 20,
    "timing__unannotated_net_filtered__count__corner:nom_ff_n40C_1v95": 0,
    "design__max_slew_violation__count__corner:min_tt_025C_1v80": 0,
    "design__max_fanout_violation__count__corner:min_tt_025C_1v80": 0,
    "design__max_cap_violation__count__corner:min_tt_025C_1v80": 0,
    "clock__skew__worst_hold__corner:min_tt_025C_1v80": -0.13800237732062987,
    "clock__skew__worst_setup__corner:min_tt_025C_1v80": 0.13671521246505156,
    "timing__hold__ws__corner:min_tt_025C_1v80": 0.34423148639216256,
    "timing__setup__ws__corner:min_tt_025C_1v80": 14.495245414251423,
    "timing__hold__tns__corner:min_tt_025C_1v80": 0,
    "timing__setup__tns__corner:min_tt_025C_1v80": 0,
    "timing__hold__wns__corner:min_tt_025C_1v80": 0,
    "timing__setup__wns__corner:min_tt_025C_1v80": 0,
    "timing__hold_vio__count__corner:min_tt_025C_1v80": 0,
    "timing__hold_r2r__ws__corner:min_tt_025C_1v80": 0.344231,
    "timing__hold_r2r_vio__count__corner:min_tt_025C_1v80": 0,
    "timing__setup_vio__count__corner:min_tt_025C_1v80": 0,
    "timing__setup_r2r__ws__corner:min_tt_025C_1v80": 14.495245,
    "timing__setup_r2r_vio__count__corner:min_tt_025C_1v80": 0,
    "timing__unannotated_net__count__corner:min_tt_025C_1v80": 20,
    "timing__unannotated_net_filtered__count__corner:min_tt_025C_1v80": 0,
    "design__max_slew_violation__count__corner:min_ss_100C_1v60": 0,
    "design__max_fanout_violation__count__corner:min_ss_100C_1v60": 0,
    "design__max_cap_violation__count__corner:min_ss_100C_1v60": 0,
    "clock__skew__worst_hold__corner:min_ss_100C_1v60": -0.1572940572313324,
    "clock__skew__worst_setup__corner:min_ss_100C_1v60": 0.15654571138041914,
    "timing__hold__ws__corner:min_ss_100C_1v60": 0.802168409957413,
    "timing__setup__ws__corner:min_ss_100C_1v60": 3.459820972091324,
    "timing__hold__tns__corner:min_ss_100C_1v60": 0,
    "timing__setup__tns__corner:min_ss_100C_1v60": 0,
    "timing__hold__wns__corner:min_ss_100C_1v60": 0,
    "timing__setup__wns__corner:min_ss_100C_1v60": 0,
    "timing__hold_vio__count__corner:min_ss_100C_1v60": 0,
    "timing__hold_r2r__ws__corner:min_ss_100C_1v60": 0.802168,
    "timing__hold_r2r_vio__count__corner:min_ss_100C_1v60": 0,
    "timing__setup_vio__count__corner:min_ss_100C_1v60": 0,
    "timing__setup_r2r__ws__corner:min_ss_100C_1v60": 3.459821,
    "timing__setup_r2r_vio__count__corner:min_ss_100C_1v60": 0,
    "timing__unannotated_net__count__corner:min_ss_100C_1v60": 20,
    "timing__unannotated_net_filtered__count__corner:min_ss_100C_1v60": 0,
    "design__max_slew_violation__count__corner:min_ff_n40C_1v95": 0,
    "design__max_fanout_violation__count__corner:min_ff_n40C_1v95": 0,
    "design__max_cap_violation__count__corner:min_ff_n40C_1v95": 0,
    "clock__skew__worst_hold__corner:min_ff_n40C_1v95": -0.12827343716953518,
    "clock__skew__worst_setup__corner:min_ff_n40C_1v95": 0.1267288393428412,
    "timing__hold__ws__corner:min_ff_n40C_1v95": 0.17701399180810815,
    "timing__setup__ws__corner:min_ff_n40C_1v95": 18.647775407204836,
    "timing__hold__tns__corner:min_ff_n40C_1v95": 0,
    "timing__setup__tns__corner:min_ff_n40C_1v95": 0,
    "timing__hold__wns__corner:min_ff_n40C_1v95": 0,
    "timing__setup__wns__corner:min_ff_n40C_1v95": 0,
    "timing__hold_vio__count__corner:min_ff_n40C_1v95": 0,
    "timing__hold_r2r__ws__corner:min_ff_n40C_1v95": 0.177014,
    "timing__hold_r2r_vio__count__corner:min_ff_n40C_1v95": 0,
    "timing__setup_vio__count__corner:min_ff_n40C_1v95": 0,
    "timing__setup_r2r__ws__corner:min_ff_n40C_1v95": 18.647776,
    "timing__setup_r2r_vio__count__corner:min_ff_n40C_1v95": 0,
    "timing__unannotated_net__count__corner:min_ff_n40C_1v95": 20,
    "timing__unannotated_net_filtered__count__corner:min_ff_n40C_1v95": 0,
    "design__max_slew_violation__count__corner:max_tt_025C_1v80": 0,
    "design__max_fanout_violation__count__corner:max_tt_025C_1v80": 0,
    "design__max_cap_violation__count__corner:max_tt_025C_1v80": 0,
    "clock__skew__worst_hold__corner:max_tt_025C_1v80": -0.14780664610607583,
    "clock__skew__worst_setup__corner:max_tt_025C_1v80": 0.14457511985690558,
    "timing__hold__ws__corner:max_tt_025C_1v80": 0.3471590890797461,
    "timing__setup__ws__corner:max_tt_025C_1v80": 14.325286251586093,
    "timing__hold__tns__corner:max_tt_025C_1v80": 0,
    "timing__setup__tns__corner:max_tt_025C_1v80": 0,
    "timing__hold__wns__corner:max_tt_025C_1v80": 0,
    "timing__setup__wns__corner:max_tt_025C_1v80": 0,
    "timing__hold_vio__count__corner:max_tt_025C_1v80": 0,
    "timing__hold_r2r__ws__corner:max_tt_025C_1v80": 0.347159,
    "timing__hold_r2r_vio__count__corner:max_tt_025C_1v80": 0,
    "timing__setup_vio__count__corner:max_tt_025C_1v80": 0,
    "timing__setup_r2r__ws__corner:max_tt_025C_1v80": 14.325286,
    "timing__setup_r2r_vio__count__corner:max_tt_025C_1v80": 0,
    "timing__unannotated_net__count__corner:max_tt_025C_1v80": 20,
    "timing__unannotated_net_filtered__count__corner:max_tt_025C_1v80": 0,
    "design__max_slew_violation__count__corner:max_ss_100C_1v60": 0,
    "design__max_fanout_violation__count__corner:max_ss_100C_1v60": 0,
    "design__max_cap_violation__count__corner:max_ss_100C_1v60": 0,
    "clock__skew__worst_hold__corner:max_ss_100C_1v60": -0.16839873028229974,
    "clock__skew__worst_setup__corner:max_ss_100C_1v60": 0.16665556906203582,
    "timing__hold__ws__corner:max_ss_100C_1v60": 0.8085849996208588,
    "timing__setup__ws__corner:max_ss_100C_1v60": 3.212500578703768,
    "timing__hold__tns__corner:max_ss_100C_1v60": 0,
    "timing__setup__tns__corner:max_ss_100C_1v60": 0,
    "timing__hold__wns__corner:max_ss_100C_1v60": 0,
    "timing__setup__wns__corner:max_ss_100C_1v60": 0,
    "timing__hold_vio__count__corner:max_ss_100C_1v60": 0,
    "timing__hold_r2r__ws__corner:max_ss_100C_1v60": 0.808585,
    "timing__hold_r2r_vio__count__corner:max_ss_100C_1v60": 0,
    "timing__setup_vio__count__corner:max_ss_100C_1v60": 0,
    "timing__setup_r2r__ws__corner:max_ss_100C_1v60": 3.212501,
    "timing__setup_r2r_vio__count__corner:max_ss_100C_1v60": 0,
    "timing__unannotated_net__count__corner:max_ss_100C_1v60": 20,
    "timing__unannotated_net_filtered__count__corner:max_ss_100C_1v60": 0,
    "design__max_slew_violation__count__corner:max_ff_n40C_1v95": 0,
    "design__max_fanout_violation__count__corner:max_ff_n40C_1v95": 0,
    "design__max_cap_violation__count__corner:max_ff_n40C_1v95": 0,
    "clock__skew__worst_hold__corner:max_ff_n40C_1v95": -0.1369580182474041,
    "clock__skew__worst_setup__corner:max_ff_n40C_1v95": 0.13342487214948842,
    "timing__hold__ws__corner:max_ff_n40C_1v95": 0.1792629706526968,
    "timing__setup__ws__corner:max_ff_n40C_1v95": 18.534941217574964,
    "timing__hold__tns__corner:max_ff_n40C_1v95": 0,
    "timing__setup__tns__corner:max_ff_n40C_1v95": 0,
    "timing__hold__wns__corner:max_ff_n40C_1v95": 0,
    "timing__setup__wns__corner:max_ff_n40C_1v95": 0,
    "timing__hold_vio__count__corner:max_ff_n40C_1v95": 0,
    "timing__hold_r2r__ws__corner:max_ff_n40C_1v95": 0.179263,
    "timing__hold_r2r_vio__count__corner:max_ff_n40C_1v95": 0,
    "timing__setup_vio__count__corner:max_ff_n40C_1v95": 0,
    "timing__setup_r2r__ws__corner:max_ff_n40C_1v95": 18.534941,
    "timing__setup_r2r_vio__count__corner:max_ff_n40C_1v95": 0,
    "timing__unannotated_net__count__corner:max_ff_n40C_1v95": 20,
    "timing__unannotated_net_filtered__count__corner:max_ff_n40C_1v95": 0,
    "timing__unannotated_net__count": 20,
    "timing__unannotated_net_filtered__count": 0,
    "design_powergrid__voltage__worst__net:VPWR__corner:nom_tt_025C_1v80": 1.79378,
    "design_powergrid__drop__average__net:VPWR__corner:nom_tt_025C_1v80": 1.79964,
    "design_powergrid__drop__worst__net:VPWR__corner:nom_tt_025C_1v80": 0.00622023,
    "design_powergrid__voltage__worst__net:VGND__corner:nom_tt_025C_1v80": 0.00629059,
    "design_powergrid__drop__average__net:VGND__corner:nom_tt_025C_1v80": 0.000358085,
    "design_powergrid__drop__worst__net:VGND__corner:nom_tt_025C_1v80": 0.00629059,
    "design_powergrid__voltage__worst": 0.00629059,
    "design_powergrid__voltage__worst__net:VPWR": 1.79378,
    "design_powergrid__drop__worst": 0.00629059,
    "design_powergrid__drop__worst__net:VPWR": 0.00622023,
    "design_powergrid__voltage__worst__net:VGND": 0.00629059,
    "design_powergrid__drop__worst__net:VGND": 0.00629059,
    "ir__voltage__worst": 1.79,
    "ir__drop__avg": 0.000361,
    "ir__drop__worst": 0.00622,
    "design__xor_difference__count": 0,
    "magic__drc_error__count": 0,
    "klayout__drc_error__count": 0,
    "magic__illegal_overlap__count": 0,
    "design__lvs_device_difference__count": 0,
    "design__lvs_net_difference__count": 0,
    "design__lvs_property_fail__count": 0,
    "design__lvs_error__count": 0,
    "design__lvs_unmatched_device__count": 0,
    "design__lvs_unmatched_net__count": 0,
    "design__lvs_unmatched_pin__count": 0
}