{
    "design__instance__count": 5385,
    "design__instance__area": 21892.2,
    "design__instance_unmapped__count": 0,
    "synthesis__check_error__count": 0,
    "design__max_slew_violation__count__corner:nom_tt_025C_1v80": 0,
    "design__max_fanout_violation__count__corner:nom_tt_025C_1v80": 0,
    "design__max_cap_violation__count__corner:nom_tt_025C_1v80": 0,
    "power__internal__total": 0.020333504304289818,
    "power__switching__total": 0.028492964804172516,
    "power__leakage__total": 2.6331786528999146e-08,
    "power__total": 0.04882649704813957,
    "clock__skew__worst_hold__corner:nom_tt_025C_1v80": -0.14539876658659368,
    "clock__skew__worst_setup__corner:nom_tt_025C_1v80": 0.13894462362827778,
    "timing__hold__ws__corner:nom_tt_025C_1v80": 0.3369453145200855,
    "timing__setup__ws__corner:nom_tt_025C_1v80": 13.586189446907968,
    "timing__hold__tns__corner:nom_tt_025C_1v80": 0,
    "timing__setup__tns__corner:nom_tt_025C_1v80": 0,
    "timing__hold__wns__corner:nom_tt_025C_1v80": 0,
    "timing__setup__wns__corner:nom_tt_025C_1v80": 0,
    "timing__hold_vio__count__corner:nom_tt_025C_1v80": 0,
    "timing__hold_r2r__ws__corner:nom_tt_025C_1v80": 0.336945,
    "timing__hold_r2r_vio__count__corner:nom_tt_025C_1v80": 0,
    "timing__setup_vio__count__corner:nom_tt_025C_1v80": 0,
    "timing__setup_r2r__ws__corner:nom_tt_025C_1v80": 13.586189,
    "timing__setup_r2r_vio__count__corner:nom_tt_025C_1v80": 0,
    "design__max_slew_violation__count__corner:nom_ss_100C_1v60": 0,
    "design__max_fanout_violation__count__corner:nom_ss_100C_1v60": 0,
    "design__max_cap_violation__count__corner:nom_ss_100C_1v60": 0,
    "clock__skew__worst_hold__corner:nom_ss_100C_1v60": -0.1669558843986904,
    "clock__skew__worst_setup__corner:nom_ss_100C_1v60": 0.16056777195663158,
    "timing__hold__ws__corner:nom_ss_100C_1v60": 0.8085135012560508,
    "timing__setup__ws__corner:nom_ss_100C_1v60": -0.8057590378540543,
    "timing__hold__tns__corner:nom_ss_100C_1v60": 0,
    "timing__setup__tns__corner:nom_ss_100C_1v60": -1.1736478787689713,
    "timing__hold__wns__corner:nom_ss_100C_1v60": 0,
    "timing__setup__wns__corner:nom_ss_100C_1v60": -0.8057590378540543,
    "timing__hold_vio__count__corner:nom_ss_100C_1v60": 0,
    "timing__hold_r2r__ws__corner:nom_ss_100C_1v60": 0.808514,
    "timing__hold_r2r_vio__count__corner:nom_ss_100C_1v60": 0,
    "timing__setup_vio__count__corner:nom_ss_100C_1v60": 3,
    "timing__setup_r2r__ws__corner:nom_ss_100C_1v60": -0.805759,
    "timing__setup_r2r_vio__count__corner:nom_ss_100C_1v60": 3,
    "design__max_slew_violation__count__corner:nom_ff_n40C_1v95": 0,
    "design__max_fanout_violation__count__corner:nom_ff_n40C_1v95": 0,
    "design__max_cap_violation__count__corner:nom_ff_n40C_1v95": 0,
    "clock__skew__worst_hold__corner:nom_ff_n40C_1v95": -0.13397229538283767,
    "clock__skew__worst_setup__corner:nom_ff_n40C_1v95": 0.1277151059946605,
    "timing__hold__ws__corner:nom_ff_n40C_1v95": 0.17544569071916807,
    "timing__setup__ws__corner:nom_ff_n40C_1v95": 18.789013543500037,
    "timing__hold__tns__corner:nom_ff_n40C_1v95": 0,
    "timing__setup__tns__corner:nom_ff_n40C_1v95": 0,
    "timing__hold__wns__corner:nom_ff_n40C_1v95": 0,
    "timing__setup__wns__corner:nom_ff_n40C_1v95": 0,
    "timing__hold_vio__count__corner:nom_ff_n40C_1v95": 0,
    "timing__hold_r2r__ws__corner:nom_ff_n40C_1v95": 0.175446,
    "timing__hold_r2r_vio__count__corner:nom_ff_n40C_1v95": 0,
    "timing__setup_vio__count__corner:nom_ff_n40C_1v95": 0,
    "timing__setup_r2r__ws__corner:nom_ff_n40C_1v95": 18.789013,
    "timing__setup_r2r_vio__count__corner:nom_ff_n40C_1v95": 0,
    "design__max_slew_violation__count": 0,
    "design__max_fanout_violation__count": 0,
    "design__max_cap_violation__count": 0,
    "clock__skew__worst_hold": -0.13024691416277134,
    "clock__skew__worst_setup": 0.1258723022551184,
    "timing__hold__ws": 0.17539115101154087,
    "timing__setup__ws": -0.9786269849261685,
    "timing__hold__tns": 0,
    "timing__setup__tns": -1.8223965075047193,
    "timing__hold__wns": 0,
    "timing__setup__wns": -0.9786269849261685,
    "timing__hold_vio__count": 0,
    "timing__hold_r2r__ws": 0.175391,
    "timing__hold_r2r_vio__count": 0,
    "timing__setup_vio__count": 9,
    "timing__setup_r2r__ws": -0.978627,
    "timing__setup_r2r_vio__count": 9,
    "design__die__bbox": "0.0 0.0 442.77 453.49",
    "design__core__bbox": "5.52 10.88 437.0 440.64",
    "design__io": 56,
    "design__die__area": 200792,
    "design__core__area": 185433,
    "design__instance__count__stdcell": 5385,
    "design__instance__area__stdcell": 21892.2,
    "design__instance__count__macros": 0,
    "design__instance__area__macros": 0,
    "design__instance__utilization": 0.11806,
    "design__instance__utilization__stdcell": 0.11806,
    "design__instance__count__class:buffer": 5,
    "design__instance__count__class:inverter": 46,
    "design__instance__count__class:sequential_cell": 138,
    "design__instance__count__class:multi_input_combinational_cell": 1635,
    "flow__warnings__count": 1,
    "flow__errors__count": 0,
    "design__instance__count__class:fill_cell": 15412,
    "design__instance__count__class:tap_cell": 2640,
    "design__power_grid_violation__count__net:VGND": 0,
    "design__power_grid_violation__count__net:VPWR": 0,
    "design__power_grid_violation__count": 0,
    "floorplan__design__io": 54,
    "design__io__hpwl": 7386243,
    "timing__drv__floating__nets": 0,
    "timing__drv__floating__pins": 0,
    "design__instance__displacement__total": 0,
    "design__instance__displacement__mean": 0,
    "design__instance__displacement__max": 0,
    "route__wirelength__estimated": 41624.4,
    "design__violations": 0,
    "design__instance__count__class:timing_repair_buffer": 53,
    "design__instance__count__class:clock_buffer": 17,
    "design__instance__count__class:clock_inverter": 15,
    "design__instance__count__setup_buffer": 0,
    "design__instance__count__hold_buffer": 0,
    "antenna__violating__nets": 1,
    "antenna__violating__pins": 1,
    "route__antenna_violation__count": 1,
    "design__instance__count__class:antenna_cell": 836,
    "antenna_diodes_count": 3,
    "route__net": 1931,
    "route__net__special": 2,
    "route__drc_errors__iter:1": 528,
    "route__wirelength__iter:1": 46288,
    "route__drc_errors__iter:2": 208,
    "route__wirelength__iter:2": 45985,
    "route__drc_errors__iter:3": 153,
    "route__wirelength__iter:3": 45986,
    "route__drc_errors__iter:4": 0,
    "route__wirelength__iter:4": 45973,
    "route__drc_errors": 0,
    "route__wirelength": 45973,
    "route__vias": 14087,
    "route__vias__singlecut": 14087,
    "route__vias__multicut": 0,
    "design__disconnected_pin__count": 0,
    "design__critical_disconnected_pin__count": 0,
    "route__wirelength__max": 1016.54,
    "timing__unannotated_net__count__corner:nom_tt_025C_1v80": 15,
    "timing__unannotated_net_filtered__count__corner:nom_tt_025C_1v80": 0,
    "timing__unannotated_net__count__corner:nom_ss_100C_1v60": 15,
    "timing__unannotated_net_filtered__count__corner:nom_ss_100C_1v60": 0,
    "timing__unannotated_net__count__corner:nom_ff_n40C_1v95": 15,
    "timing__unannotated_net_filtered__count__corner:nom_ff_n40C_1v95": 0,
    "design__max_slew_violation__count__corner:min_tt_025C_1v80": 0,
    "design__max_fanout_violation__count__corner:min_tt_025C_1v80": 0,
    "design__max_cap_violation__count__corner:min_tt_025C_1v80": 0,
    "clock__skew__worst_hold__corner:min_tt_025C_1v80": -0.14081249065330964,
    "clock__skew__worst_setup__corner:min_tt_025C_1v80": 0.1364846468918917,
    "timing__hold__ws__corner:min_tt_025C_1v80": 0.33757853024008905,
    "timing__setup__ws__corner:min_tt_025C_1v80": 13.68593010990431,
    "timing__hold__tns__corner:min_tt_025C_1v80": 0,
    "timing__setup__tns__corner:min_tt_025C_1v80": 0,
    "timing__hold__wns__corner:min_tt_025C_1v80": 0,
    "timing__setup__wns__corner:min_tt_025C_1v80": 0,
    "timing__hold_vio__count__corner:min_tt_025C_1v80": 0,
    "timing__hold_r2r__ws__corner:min_tt_025C_1v80": 0.337579,
    "timing__hold_r2r_vio__count__corner:min_tt_025C_1v80": 0,
    "timing__setup_vio__count__corner:min_tt_025C_1v80": 0,
    "timing__setup_r2r__ws__corner:min_tt_025C_1v80": 13.68593,
    "timing__setup_r2r_vio__count__corner:min_tt_025C_1v80": 0,
    "timing__unannotated_net__count__corner:min_tt_025C_1v80": 15,
    "timing__unannotated_net_filtered__count__corner:min_tt_025C_1v80": 0,
    "design__max_slew_violation__count__corner:min_ss_100C_1v60": 0,
    "design__max_fanout_violation__count__corner:min_ss_100C_1v60": 0,
    "design__max_cap_violation__count__corner:min_ss_100C_1v60": 0,
    "clock__skew__worst_hold__corner:min_ss_100C_1v60": -0.1610011475265507,
    "clock__skew__worst_setup__corner:min_ss_100C_1v60": 0.15706984768516827,
    "timing__hold__ws__corner:min_ss_100C_1v60": 0.8092655663542018,
    "timing__setup__ws__corner:min_ss_100C_1v60": -0.6396625632452442,
    "timing__hold__tns__corner:min_ss_100C_1v60": 0,
    "timing__setup__tns__corner:min_ss_100C_1v60": -0.7918785851184147,
    "timing__hold__wns__corner:min_ss_100C_1v60": 0,
    "timing__setup__wns__corner:min_ss_100C_1v60": -0.6396625632452442,
    "timing__hold_vio__count__corner:min_ss_100C_1v60": 0,
    "timing__hold_r2r__ws__corner:min_ss_100C_1v60": 0.809266,
    "timing__hold_r2r_vio__count__corner:min_ss_100C_1v60": 0,
    "timing__setup_vio__count__corner:min_ss_100C_1v60": 2,
    "timing__setup_r2r__ws__corner:min_ss_100C_1v60": -0.639663,
    "timing__setup_r2r_vio__count__corner:min_ss_100C_1v60": 2,
    "timing__unannotated_net__count__corner:min_ss_100C_1v60": 15,
    "timing__unannotated_net_filtered__count__corner:min_ss_100C_1v60": 0,
    "design__max_slew_violation__count__corner:min_ff_n40C_1v95": 0,
    "design__max_fanout_violation__count__corner:min_ff_n40C_1v95": 0,
    "design__max_cap_violation__count__corner:min_ff_n40C_1v95": 0,
    "clock__skew__worst_hold__corner:min_ff_n40C_1v95": -0.13024691416277134,
    "clock__skew__worst_setup__corner:min_ff_n40C_1v95": 0.1258723022551184,
    "timing__hold__ws__corner:min_ff_n40C_1v95": 0.17570834173864705,
    "timing__setup__ws__corner:min_ff_n40C_1v95": 18.855436856674313,
    "timing__hold__tns__corner:min_ff_n40C_1v95": 0,
    "timing__setup__tns__corner:min_ff_n40C_1v95": 0,
    "timing__hold__wns__corner:min_ff_n40C_1v95": 0,
    "timing__setup__wns__corner:min_ff_n40C_1v95": 0,
    "timing__hold_vio__count__corner:min_ff_n40C_1v95": 0,
    "timing__hold_r2r__ws__corner:min_ff_n40C_1v95": 0.175708,
    "timing__hold_r2r_vio__count__corner:min_ff_n40C_1v95": 0,
    "timing__setup_vio__count__corner:min_ff_n40C_1v95": 0,
    "timing__setup_r2r__ws__corner:min_ff_n40C_1v95": 18.855436,
    "timing__setup_r2r_vio__count__corner:min_ff_n40C_1v95": 0,
    "timing__unannotated_net__count__corner:min_ff_n40C_1v95": 15,
    "timing__unannotated_net_filtered__count__corner:min_ff_n40C_1v95": 0,
    "design__max_slew_violation__count__corner:max_tt_025C_1v80": 0,
    "design__max_fanout_violation__count__corner:max_tt_025C_1v80": 0,
    "design__max_cap_violation__count__corner:max_tt_025C_1v80": 0,
    "clock__skew__worst_hold__corner:max_tt_025C_1v80": -0.1520944385707477,
    "clock__skew__worst_setup__corner:max_tt_025C_1v80": 0.14140565507656708,
    "timing__hold__ws__corner:max_tt_025C_1v80": 0.3369854490835608,
    "timing__setup__ws__corner:max_tt_025C_1v80": 13.487814802359757,
    "timing__hold__tns__corner:max_tt_025C_1v80": 0,
    "timing__setup__tns__corner:max_tt_025C_1v80": 0,
    "timing__hold__wns__corner:max_tt_025C_1v80": 0,
    "timing__setup__wns__corner:max_tt_025C_1v80": 0,
    "timing__hold_vio__count__corner:max_tt_025C_1v80": 0,
    "timing__hold_r2r__ws__corner:max_tt_025C_1v80": 0.336985,
    "timing__hold_r2r_vio__count__corner:max_tt_025C_1v80": 0,
    "timing__setup_vio__count__corner:max_tt_025C_1v80": 0,
    "timing__setup_r2r__ws__corner:max_tt_025C_1v80": 13.487815,
    "timing__setup_r2r_vio__count__corner:max_tt_025C_1v80": 0,
    "timing__unannotated_net__count__corner:max_tt_025C_1v80": 15,
    "timing__unannotated_net_filtered__count__corner:max_tt_025C_1v80": 0,
    "design__max_slew_violation__count__corner:max_ss_100C_1v60": 0,
    "design__max_fanout_violation__count__corner:max_ss_100C_1v60": 0,
    "design__max_cap_violation__count__corner:max_ss_100C_1v60": 0,
    "clock__skew__worst_hold__corner:max_ss_100C_1v60": -0.17464023776981058,
    "clock__skew__worst_setup__corner:max_ss_100C_1v60": 0.16383127262981534,
    "timing__hold__ws__corner:max_ss_100C_1v60": 0.8090617294011158,
    "timing__setup__ws__corner:max_ss_100C_1v60": -0.9786269849261685,
    "timing__hold__tns__corner:max_ss_100C_1v60": 0,
    "timing__setup__tns__corner:max_ss_100C_1v60": -1.8223965075047193,
    "timing__hold__wns__corner:max_ss_100C_1v60": 0,
    "timing__setup__wns__corner:max_ss_100C_1v60": -0.9786269849261685,
    "timing__hold_vio__count__corner:max_ss_100C_1v60": 0,
    "timing__hold_r2r__ws__corner:max_ss_100C_1v60": 0.809062,
    "timing__hold_r2r_vio__count__corner:max_ss_100C_1v60": 0,
    "timing__setup_vio__count__corner:max_ss_100C_1v60": 4,
    "timing__setup_r2r__ws__corner:max_ss_100C_1v60": -0.978627,
    "timing__setup_r2r_vio__count__corner:max_ss_100C_1v60": 4,
    "timing__unannotated_net__count__corner:max_ss_100C_1v60": 15,
    "timing__unannotated_net_filtered__count__corner:max_ss_100C_1v60": 0,
    "design__max_slew_violation__count__corner:max_ff_n40C_1v95": 0,
    "design__max_fanout_violation__count__corner:max_ff_n40C_1v95": 0,
    "design__max_cap_violation__count__corner:max_ff_n40C_1v95": 0,
    "clock__skew__worst_hold__corner:max_ff_n40C_1v95": -0.13992683796594257,
    "clock__skew__worst_setup__corner:max_ff_n40C_1v95": 0.12978164743556792,
    "timing__hold__ws__corner:max_ff_n40C_1v95": 0.17539115101154087,
    "timing__setup__ws__corner:max_ff_n40C_1v95": 18.72237173842834,
    "timing__hold__tns__corner:max_ff_n40C_1v95": 0,
    "timing__setup__tns__corner:max_ff_n40C_1v95": 0,
    "timing__hold__wns__corner:max_ff_n40C_1v95": 0,
    "timing__setup__wns__corner:max_ff_n40C_1v95": 0,
    "timing__hold_vio__count__corner:max_ff_n40C_1v95": 0,
    "timing__hold_r2r__ws__corner:max_ff_n40C_1v95": 0.175391,
    "timing__hold_r2r_vio__count__corner:max_ff_n40C_1v95": 0,
    "timing__setup_vio__count__corner:max_ff_n40C_1v95": 0,
    "timing__setup_r2r__ws__corner:max_ff_n40C_1v95": 18.722372,
    "timing__setup_r2r_vio__count__corner:max_ff_n40C_1v95": 0,
    "timing__unannotated_net__count__corner:max_ff_n40C_1v95": 15,
    "timing__unannotated_net_filtered__count__corner:max_ff_n40C_1v95": 0,
    "timing__unannotated_net__count": 15,
    "timing__unannotated_net_filtered__count": 0,
    "design_powergrid__voltage__worst__net:VPWR__corner:nom_tt_025C_1v80": 1.79358,
    "design_powergrid__drop__average__net:VPWR__corner:nom_tt_025C_1v80": 1.79956,
    "design_powergrid__drop__worst__net:VPWR__corner:nom_tt_025C_1v80": 0.00641862,
    "design_powergrid__voltage__worst__net:VGND__corner:nom_tt_025C_1v80": 0.0054796,
    "design_powergrid__drop__average__net:VGND__corner:nom_tt_025C_1v80": 0.000437185,
    "design_powergrid__drop__worst__net:VGND__corner:nom_tt_025C_1v80": 0.0054796,
    "design_powergrid__voltage__worst": 0.0054796,
    "design_powergrid__voltage__worst__net:VPWR": 1.79358,
    "design_powergrid__drop__worst": 0.00641862,
    "design_powergrid__drop__worst__net:VPWR": 0.00641862,
    "design_powergrid__voltage__worst__net:VGND": 0.0054796,
    "design_powergrid__drop__worst__net:VGND": 0.0054796,
    "ir__voltage__worst": 1.79,
    "ir__drop__avg": 0.00044,
    "ir__drop__worst": 0.00642,
    "design__xor_difference__count": 0,
    "magic__drc_error__count": 0,
    "klayout__drc_error__count": 0,
    "magic__illegal_overlap__count": 0,
    "design__lvs_device_difference__count": 0,
    "design__lvs_net_difference__count": 0,
    "design__lvs_property_fail__count": 0,
    "design__lvs_error__count": 0,
    "design__lvs_unmatched_device__count": 0,
    "design__lvs_unmatched_net__count": 0,
    "design__lvs_unmatched_pin__count": 0
}