{
    "time": {
        "cpu_time_user": "00:00:36.229",
        "cpu_time_system": "00:00:00.540",
        "runtime": "00:00:33.954",
        "cpu_time_iowait": "00:00:00.000"
    },
    "peak_resources": {
        "cpu_percent": 398.2,
        "memory_rss": "652MiB",
        "memory_vms": "1GiB",
        "threads": 9
    },
    "avg_resources": {
        "cpu_percent": 107.65235294117637,
        "memory_rss": "530MiB",
        "memory_vms": "1GiB",
        "threads": 3.9823529411764684
    }
}